cancellation_policy_pkg/CancellationPolicyLib.py
cancellation_policy_pkg/__init__.py
tests/__init__.py
tests/test_cancellation_policy_pkg.py
cn_cancellation_policy_pkg-0.3.9.dist-info/METADATA
cn_cancellation_policy_pkg-0.3.9.dist-info/WHEEL
cn_cancellation_policy_pkg-0.3.9.dist-info/top_level.txt
cn_cancellation_policy_pkg-0.3.9.dist-info/RECORD
