Metadata-Version: 2.1
Name: cn_cancellation_policy_pkg
Version: 0.3.9
Summary: A library for parsing cancellation policies
Author: Khalil Raza
Author-email: khalilraza49@gmail.com
Keywords: cancellation policy parser
Classifier: Programming Language :: Python :: 3
Classifier: License :: OSI Approved :: MIT License
Classifier: Operating System :: OS Independent
